{
  "config": {
    "step": {
      "user": {
        "title": "Estada einrichten",
        "description": "Bitte gib die Client ID für diese Estada-Installation ein.",
        "data": {
          "client_id": "Client ID"
        }
      },
      "reconfigure": {
        "title": "Estada neu konfigurieren",
        "description": "Passe die Client ID dieser Estada-Installation an.",
        "data": {
          "client_id": "Client ID"
        }
      }
    },
    "error": {
      "client_id_required": "Bitte gib eine Client ID ein."
    },
    "abort": {
      "already_configured": "Diese Client ID ist bereits eingerichtet."
    }
  }
}
